dreamstone/__init__.py
dreamstone/cli/main.py
dreamstone/core/decryption.py
dreamstone/core/encryption.py
dreamstone/core/keys.py
dreamstone/core/password.py
dreamstone/models/payload.py
dreamstone-0.1.6.post1.dist-info/LICENSE
dreamstone-0.1.6.post1.dist-info/METADATA
dreamstone-0.1.6.post1.dist-info/WHEEL
dreamstone-0.1.6.post1.dist-info/entry_points.txt
dreamstone-0.1.6.post1.dist-info/RECORD
