Metadata-Version: 2.3
Name: dreamstone
Version: 0.1.6.post1
Summary: Secure hybrid RSA + AES encryption library with CLI
License: MIT
Author: Renks
Requires-Python: >=3.10,<4.0
Classifier: License :: OSI Approved :: MIT License
Classifier: Programming Language :: Python :: 3
Classifier: Programming Language :: Python :: 3.10
Classifier: Programming Language :: Python :: 3.11
Classifier: Programming Language :: Python :: 3.12
Classifier: Programming Language :: Python :: 3.13
Requires-Dist: cryptography (>=45.0.5,<46.0.0)
Requires-Dist: typer[all] (>=0.16.0,<0.17.0)
